ghostsignal/__init__.py
ghostsignal/main.py
ghostsignal/core/__init__.py
ghostsignal/core/anuj_ai.py
ghostsignal/core/face_search.py
ghostsignal/security/__init__.py
ghostsignal/security/auth.py
ghostsignal/ui/__init__.py
ghostsignal/ui/terminal_ui.py
ghostsignal-0.1.2.dist-info/METADATA
ghostsignal-0.1.2.dist-info/WHEEL
ghostsignal-0.1.2.dist-info/entry_points.txt
ghostsignal-0.1.2.dist-info/top_level.txt
ghostsignal-0.1.2.dist-info/RECORD
